{
  "symbol": "MEAN",
  "name": "Mean Finance",
  "maxSupply": 210000000,
  "totalSupply": 210000000,
  "address": "MEANeD3XDdUmNMsRGjASkSWdC8prLYsoRJ61pPeHctD",
  "circulatingSupply": 96696974.488645,
  "holders": 11910,
  "marketCap": 15340878.305649042,
  "marketCapFD": 33316290.000000004,
  "tvl": {
    "symbol": "USD",
    "total": 31782893.48,
    "lastUpdateUtc": "2022-09-10T16:38:40.018Z",
    "totalStreams": 52942
  },
  "lastUpdateUtc": "2022-09-10T17:10:24.637Z",
  "version": "2.0.0"
}